quran_search_in_text/__init__.py
quran_search_in_text/ayeh_yab.py
quran_search_in_text/packages/ayat.txt
quran_search_in_text/packages/surehname_ayehnumber.txt
quran_search_in_text/packages/surehnumber_ayehnumber.txt
quran_search_in_text-0.1.3.dist-info/LICENSE
quran_search_in_text-0.1.3.dist-info/METADATA
quran_search_in_text-0.1.3.dist-info/WHEEL
quran_search_in_text-0.1.3.dist-info/top_level.txt
quran_search_in_text-0.1.3.dist-info/RECORD
