Metadata-Version: 2.1
Name: quran_search_in_text
Version: 0.1.3
Summary: package for find verses in text
Author-email: Reza jafarzadeh <rezajafar90@gmail.com>
Project-URL: Homepage, https://github.com/pypa/sampleproject
Project-URL: Issues, https://github.com/pypa/sampleproject/issues
Keywords: quran,verse,ayeh,ayat,kuran,Quran
Classifier: Programming Language :: Python :: 3
Classifier: License :: OSI Approved :: MIT License
Classifier: Operating System :: OS Independent
Requires-Python: >=3.8
License-File: LICENSE
Requires-Dist: bs4
